[
   {
      "nada": 0,
      "store": "Steam",
      "coming": 0,
      "name": "PUBG: BATTLEGROUNDS",
      "image": "https://i.ibb.co/L8D5hLr/PUBG.jpg",
      "background": "",
      "description": "",
      "price": "$20.00",
      "date": "2022",
      "url": "https://bit.ly/3Ap3xO3"
   },
   {
      "coming": 0,
      "nada": 0,
      "store": "Indiegala",
      "name": "Byte Family",
      "image": "https://i.ibb.co/9vMBdGT/Byte-Family.jpg",
      "background": "",
      "description": " ",
      "price": "$5.00",
      "date": "Jan ?? 2022",
      "url": "https://bit.ly/34s08Dj"
   },
   {
      "coming": 0,
      "nada": 0,
      "store": "Microsoft",
      "name": "Rabbit of Destiny",
      "image": "https://i.ibb.co/TPmNhzb/Rabbitof-Destiny.jpg",
      "background": "",
      "description": " ",
      "price": "$5.00",
      "date": "Jan ?? 2022",
      "url": "https://bit.ly/3eWrsvt"
   },
   {
      "nada": 0,
      "store": "Steam - DLC",
      "coming": 0,
      "name": "DLC - Minion Masters - Invasion",
      "image": "https://i.ibb.co/qrHyb8z/Minion.jpg",
      "background": "",
      "description": "",
      "price": "$9.00",
      "date": "Jan ?? 2022",
      "url": "https://bit.ly/3t1uHdd"
   },
   {
      "coming": 0,
      "nada": 0,
      "store": "Microsoft",
      "name": "Farming Simulator 16",
      "image": "https://i.ibb.co/gJCN5bt/Farming-Simulator16.jpg",
      "background": "",
      "description": " ",
      "price": "$5.00",
      "date": "Jan ?? 2022",
      "url": "https://bit.ly/3zvgAOK"
   },
   {
      "coming": 0,
      "nada": 0,
      "store": "Indiegala",
      "name": "Garfield Kart",
      "image": "https://i.ibb.co/vzwB6ps/garfieldkart.jpg",
      "background": "",
      "description": " ",
      "price": "$1.29",
      "date": "Jan ?? 2022",
      "url": "https://bit.ly/3a8rTkZ"
   },
   {
      "nada": 0,
      "store": "GoG",
      "coming": 0,
      "name": "Iratus: Lord of the Dead",
      "image": "https://i.ibb.co/xMDW5K4/Iratus.jpg",
      "background": "",
      "description": "",
      "price": "$0.00",
      "date": "Jan 05 2022",
      "url": "https://bit.ly/3y9mD9d"
   },
   {
      "coming": 0,
      "nada": 0,
      "store": "Indiegala",
      "name": "Toree 3D",
      "image": "https://i.ibb.co/g7nCQgK/Toree3D.jpg",
      "background": "",
      "description": " ",
      "price": "$5.00",
      "date": "Jan ?? 2022",
      "url": "https://bit.ly/3zqo9WP"
   },
   {
      "coming": 0,
      "nada": 0,
      "store": "Indiegala",
      "name": "Nostradamus: The Last Prophecy",
      "image": "https://i.ibb.co/ZYQHYR6/Nostradamus-The-Last-Prophecy.jpg",
      "background": "",
      "description": " ",
      "price": "$5.00",
      "date": "Jan ?? 2022",
      "url": "https://bit.ly/3HrwaxC"
   },
   {
      "nada": 0,
      "store": "Steam",
      "coming": 0,
      "name": "Halo Infinite",
      "image": "https://i.ibb.co/CHBR1ps/haloinfinite.jpg",
      "background": "",
      "description": "",
      "price": "$0.00",
      "date": "Jan ?? 2022",
      "url": "https://bit.ly/3HAUXAd"
   },
   {
      "nada": 0,
      "store": "Steam",
      "coming": 0,
      "name": "[NA/EU] Black Desert - FREE Gift Pack",
      "image": "https://i.ibb.co/DW8mNmT/NAEUBlack-Desert-FREEGift-Pack.jpg",
      "background": "",
      "description": "",
      "price": "$0.00",
      "date": "2022",
      "url": "https://bit.ly/3DQSzT0"
   },
   {
      "nada": 0,
      "store": "Microsoft",
      "coming": 0,
      "name": "MINECRAFT: EMERALD TYCOON",
      "image": "https://i.ibb.co/zSZcvHK/MINECRAFTEMERALDTYCOON.jpg",
      "background": "",
      "description": "",
      "price": "$5.00",
      "date": "2022",
      "url": "https://bit.ly/3lCDBbL"
   },
   {
      "coming": 0,
      "nada": 0,
      "store": "Steam",
      "name": "PAYDAY 2 DLCS",
      "image": "https://i.ibb.co/DVkV26g/pd2-socialmedia.png",
      "background": "   ",
      "description": " ",
      "price": "$?.?",
      "date": "2022",
      "url": "https://bit.ly/3jTTfO0"
   },
   {
      "coming": 0,
      "nada": 0,
      "store": "Indiegala",
      "name": "Holiday Bonus GOLD",
      "image": "https://i.ibb.co/Rym7226/Holiday-Bonus-GOLD.jpg",
      "background": "",
      "description": " ",
      "price": "$5.00",
      "date": "Jan ?? 2022",
      "url": "https://bit.ly/3HmPxYs"
   },
   {
      "coming": 0,
      "nada": 0,
      "store": "Itch.io",
      "name": "Ryza Roads",
      "image": "https://i.ibb.co/vsYTNNz/ryzaroads.jpg",
      "background": "",
      "description": " ",
      "price": "$3.99",
      "date": "Jan ?? 2022",
      "url": "https://bit.ly/2HC1G2K"
   },
   {
      "nada": 0,
      "store": "Indiegala",
      "coming": 0,
      "name": "Santa Rockstar",
      "image": "https://i.ibb.co/qdwG8bL/Santa-Rockstar.jpg",
      "background": "",
      "description": "",
      "price": "$5.00",
      "date": "Jan ?? 2022",
      "url": "https://bit.ly/3FzhDiY"
   },
   {
      "coming": 0,
      "nada": 0,
      "store": "Indiegala",
      "name": "Pixel Puzzles 2: Christmas",
      "image": "https://i.ibb.co/CbFL6rp/pixel2puzzles.jpg",
      "background": "",
      "description": " ",
      "price": "$5.00",
      "date": "Jan ?? 2022",
      "url": "https://bit.ly/3egt7Me"
   },
   {
      "nada": 0,
      "store": "Steam",
      "coming": 0,
      "name": "Ann",
      "image": "https://i.ibb.co/K6XWcNV/Ann.jpg",
      "background": "",
      "description": "",
      "price": "$5.00",
      "date": "Jan ?? 2022",
      "url": "https://bit.ly/3wlUXPf"
   },
   {
      "nada": 0,
      "store": "Itch.io",
      "coming": 0,
      "name": "Red Trees",
      "image": "https://i.ibb.co/D7PFB83/RedTrees.jpg",
      "background": "",
      "description": "",
      "price": "$5.00",
      "date": "Jan ?? 2022",
      "url": "https://bit.ly/3CyF4am"
   },
   {
      "coming": 0,
      "nada": 0,
      "store": "Indiegala",
      "name": "Die Young: Prologue",
      "image": "https://i.ibb.co/6yQHc19/Die-Young-Prologue.jpg",
      "background": "",
      "description": " ",
      "price": "$7.99",
      "date": "Jan ?? 2022",
      "url": "https://bit.ly/2M22QWO"
   },
   {
      "nada": 0,
      "store": "Steam",
      "coming": 0,
      "name": "Quake II RTX Steam",
      "image": "https://i.ibb.co/WG4DVDL/Quake-IIRTX.jpg",
      "background": "",
      "description": "",
      "price": "$0.00",
      "date": "2022",
      "url": "https://bit.ly/3yLsXnL"
   },
   {
      "nada": 0,
      "store": "GoG",
      "coming": 0,
      "name": "Quake II RTX GoG",
      "image": "https://i.ibb.co/RjrhRPh/Quake-IIRTXGo-G.jpg",
      "background": "",
      "description": "",
      "price": "$0.00",
      "date": "2022",
      "url": "https://bit.ly/3y9mD9d"
   },
   {
      "nada": 0,
      "store": "GoG",
      "coming": 0,
      "name": "Symphonia",
      "image": "https://i.ibb.co/S7D7Rmg/Symphonia.jpg",
      "background": "",
      "description": "",
      "price": "$0.00",
      "date": "2022",
      "url": "https://bit.ly/3i054CB"
   },
   {
      "coming": 0,
      "nada": 0,
      "store": "Steam",
      "name": "Vecter",
      "image": "https://i.ibb.co/1sP3734/vecter.jpg",
      "background": "",
      "description": " ",
      "price": "$2.49",
      "date": "2022",
      "url": "https://bit.ly/3793DxU"
   }
]