[
   {
      "coming": 0,
      "nada": 0,
      "store": "Steam",
      "name": "For Honor",
      "image": "https://store.ubi.com/dw/image/v2/ABBS_PRD/on/demandware.static/-/Sites-masterCatalog/la/dw5e68e4ff/images/large/5759633788a7e3de678b4567.jpg?sw=341&sh=450&sm=fit",
      "background": "",
      "description": " ",
      "price": "$4.50",
      "date": "Jan 31 2022",
      "url": "https://bit.ly/3G5R9VA"
   },
   {
      "coming": 0,
      "nada": 0,
      "store": "Steam - VR",
      "name": "STAR WARS™: Squadrons",
      "image": "https://cdn.akamai.steamstatic.com/steam/apps/1222730/header.jpg?t=1643061436",
      "background": "",
      "description": " ",
      "price": "$4.50",
      "date": "Jan 31 2022",
      "url": "https://bit.ly/3KJ81oJ"
   },
   {
      "nada": 1,
      "store": "Steam",
      "name": "",
      "image": "https://i.ibb.co/WVtNy20/white.jpg",
      "background": "",
      "description": "",
      "price": " ",
      "date": " ",
      "url": "https://freeepicgames.me"
   }
]